Report_of_Monaco_2018_Racing_Volodymyr_Perehuda/__init__.py
Report_of_Monaco_2018_Racing_Volodymyr_Perehuda/report.py
report_of_monaco_2018_racing_volodymyr_perehuda-0.0.1.dist-info/METADATA
report_of_monaco_2018_racing_volodymyr_perehuda-0.0.1.dist-info/WHEEL
report_of_monaco_2018_racing_volodymyr_perehuda-0.0.1.dist-info/RECORD
